setup.py
applicationinsights_jupyter/__init__.py
applicationinsights_jupyter/jupyter.py
applicationinsights_jupyter.egg-info/PKG-INFO
applicationinsights_jupyter.egg-info/SOURCES.txt
applicationinsights_jupyter.egg-info/dependency_links.txt
applicationinsights_jupyter.egg-info/not-zip-safe
applicationinsights_jupyter.egg-info/top_level.txt