Metadata-Version: 1.0
Name: applicationinsights-jupyter
Version: 0.6
Summary: Easy querying of Application Insights data for Jupyter
Home-page: http://github.com/jacobmsft/ApplicationInsights_Jupyter
Author: Suraj Jacob
Author-email: jacob.suraj@live.com
License: MIT
Platform: UNKNOWN
